ocr_helper/__init__.py
ocr_helper/core/__init__.py
ocr_helper/core/baidu.py
ocr_helper/utils/__init__.py
ocr_helper/utils/image_utils.py
python_ocr_helper-0.0.2.dist-info/licenses/LICENSE
python_ocr_helper-0.0.2.dist-info/METADATA
python_ocr_helper-0.0.2.dist-info/WHEEL
python_ocr_helper-0.0.2.dist-info/top_level.txt
python_ocr_helper-0.0.2.dist-info/RECORD
